my_orm_library/__init__.py
my_orm_library/models.py
my_orm_lib-0.1.1.dist-info/METADATA
my_orm_lib-0.1.1.dist-info/WHEEL
my_orm_lib-0.1.1.dist-info/top_level.txt
my_orm_lib-0.1.1.dist-info/RECORD
